{
  "version": 2,
  "extractor": "papercropper",
  "figures": [
    {
      "url": "assets/figures/openreview/openreview-icml-2025-ymlwqfxuuc/fig-001.webp",
      "caption": "",
      "page": 0,
      "index": 1,
      "width": 1248,
      "height": 426,
      "label": "Figure"
    },
    {
      "url": "assets/figures/openreview/openreview-icml-2025-ymlwqfxuuc/fig-002.webp",
      "caption": "",
      "page": 0,
      "index": 2,
      "width": 877,
      "height": 411,
      "label": "Figure"
    },
    {
      "url": "assets/figures/openreview/openreview-icml-2025-ymlwqfxuuc/fig-003.webp",
      "caption": "",
      "page": 0,
      "index": 3,
      "width": 629,
      "height": 976,
      "label": "Figure"
    },
    {
      "url": "assets/figures/openreview/openreview-icml-2025-ymlwqfxuuc/fig-004.webp",
      "caption": "",
      "page": 0,
      "index": 4,
      "width": 625,
      "height": 955,
      "label": "Figure"
    },
    {
      "url": "assets/figures/openreview/openreview-icml-2025-ymlwqfxuuc/fig-005.webp",
      "caption": "",
      "page": 0,
      "index": 5,
      "width": 614,
      "height": 892,
      "label": "Figure"
    },
    {
      "url": "assets/figures/openreview/openreview-icml-2025-ymlwqfxuuc/fig-006.webp",
      "caption": "",
      "page": 0,
      "index": 6,
      "width": 608,
      "height": 988,
      "label": "Figure"
    },
    {
      "url": "assets/figures/openreview/openreview-icml-2025-ymlwqfxuuc/fig-007.webp",
      "caption": "",
      "page": 0,
      "index": 7,
      "width": 1645,
      "height": 582,
      "label": "Figure"
    },
    {
      "url": "assets/figures/openreview/openreview-icml-2025-ymlwqfxuuc/fig-008.webp",
      "caption": "",
      "page": 0,
      "index": 8,
      "width": 822,
      "height": 269,
      "label": "Figure"
    },
    {
      "url": "assets/figures/openreview/openreview-icml-2025-ymlwqfxuuc/fig-009.webp",
      "caption": "",
      "page": 0,
      "index": 9,
      "width": 757,
      "height": 575,
      "label": "Figure"
    },
    {
      "url": "assets/figures/openreview/openreview-icml-2025-ymlwqfxuuc/fig-010.webp",
      "caption": "",
      "page": 0,
      "index": 10,
      "width": 619,
      "height": 264,
      "label": "Figure"
    },
    {
      "url": "assets/figures/openreview/openreview-icml-2025-ymlwqfxuuc/fig-011.webp",
      "caption": "",
      "page": 0,
      "index": 11,
      "width": 1674,
      "height": 593,
      "label": "Figure"
    },
    {
      "url": "assets/figures/openreview/openreview-icml-2025-ymlwqfxuuc/fig-012.webp",
      "caption": "",
      "page": 0,
      "index": 12,
      "width": 1677,
      "height": 818,
      "label": "Figure"
    },
    {
      "url": "assets/figures/openreview/openreview-icml-2025-ymlwqfxuuc/fig-013.webp",
      "caption": "",
      "page": 0,
      "index": 13,
      "width": 1660,
      "height": 597,
      "label": "Figure"
    }
  ]
}